bioconverter/__init__.py
bioconverter/cli.py
bioconverter/conversion_report.py
bioconverter/convertor.py
bioconverter/interactive_converter.py
bioconverter-0.1.4.dist-info/licenses/LICENSE
bioconverter-0.1.4.dist-info/METADATA
bioconverter-0.1.4.dist-info/WHEEL
bioconverter-0.1.4.dist-info/entry_points.txt
bioconverter-0.1.4.dist-info/top_level.txt
bioconverter-0.1.4.dist-info/RECORD
