Metadata-Version: 2.4
Name: bioconverter
Version: 0.1.4
Summary: Universal bioinformatics data converter for multi-omics data formats
Home-page: https://github.com/Jeblqr/bioConv
Author: jeblqr
Author-email: 
Project-URL: Bug Reports, https://github.com/Jeblqr/bioConv/issues
Project-URL: Source, https://github.com/Jeblqr/bioConv
Project-URL: Documentation, https://github.com/Jeblqr/bioConv/blob/main/README.md
Keywords: bioinformatics genomics transcriptomics proteomics metabolomics data-conversion
Classifier: Development Status :: 4 - Beta
Classifier: Intended Audience :: Science/Research
Classifier: Topic :: Scientific/Engineering :: Bio-Informatics
Classifier: License :: OSI Approved :: MIT License
Classifier: Programming Language :: Python :: 3
Classifier: Programming Language :: Python :: 3.8
Classifier: Programming Language :: Python :: 3.9
Classifier: Programming Language :: Python :: 3.10
Classifier: Programming Language :: Python :: 3.11
Classifier: Programming Language :: Python :: 3.12
Requires-Python: >=3.8
License-File: LICENSE
Requires-Dist: pandas>=2.0.0
Requires-Dist: numpy>=1.24.0
Requires-Dist: pyarrow>=12.0.0
Provides-Extra: dev
Requires-Dist: pytest>=7.0.0; extra == "dev"
Requires-Dist: pytest-cov>=4.0.0; extra == "dev"
Requires-Dist: black>=22.0.0; extra == "dev"
Requires-Dist: flake8>=5.0.0; extra == "dev"
Dynamic: author
Dynamic: classifier
Dynamic: description
Dynamic: description-content-type
Dynamic: home-page
Dynamic: keywords
Dynamic: license-file
Dynamic: project-url
Dynamic: provides-extra
Dynamic: requires-dist
Dynamic: requires-python
Dynamic: summary
